libmaya-0.2.0.dist-info/METADATA
libmaya-0.2.0.dist-info/RECORD
libmaya-0.2.0.dist-info/WHEEL
libmaya-0.2.0.dist-info/entry_points.txt
libmaya-0.2.0.dist-info/top_level.txt
maya/KeySpot_op.py
maya/__init__.py
maya/andrew_exp.py
maya/exp_runner/__init__.py
maya/exp_runner/batch_command.py
maya/exp_runner/command_runner.py
maya/exp_runner/dataset_processor.py
maya/exp_runner/from_template.py
maya/exp_runner/maya.py
maya/exp_runner/maya_utils.py
maya/exp_runner/result_processor.py
maya/exp_runner/utils.py
maya/exp_runner/wav_processor.py
